pyasassn/__init__.py
pyasassn/client.py
pyasassn/collection.py
pyasassn/lightcurve.py
pyasassn/utils.py
pyasassn/version.py
pyasassn/wavelet.py
skypatrol-0.6.21.dist-info/licenses/LICENSE
skypatrol-0.6.21.dist-info/METADATA
skypatrol-0.6.21.dist-info/WHEEL
skypatrol-0.6.21.dist-info/top_level.txt
skypatrol-0.6.21.dist-info/RECORD
