Metadata-Version: 2.4
Name: skypatrol
Version: 0.6.21
Home-page: https://github.com/asas_sn/skypatrol/
Author: ASAS-SN
Author-email: kylehart@hawaii.edu
License: GPL v.3
License-File: LICENSE
Requires-Dist: requests
Requires-Dist: pandas
Requires-Dist: pyarrow
Requires-Dist: astropy
Requires-Dist: numpy
Requires-Dist: matplotlib
Requires-Dist: tqdm>=4.65.0
Dynamic: author
Dynamic: author-email
Dynamic: home-page
Dynamic: license
Dynamic: license-file
Dynamic: requires-dist
